srtm-0.2.0.dist-info/METADATA
srtm-0.2.0.dist-info/WHEEL
srtm/__init__.py
srtm/__init__.pyi
srtm/srtm.cpython-312-darwin.so
srtm-0.2.0.dist-info/RECORD
