Metadata-Version: 2.4
Name: srtm
Version: 0.2.0
Classifier: Development Status :: 4 - Beta
Classifier: Intended Audience :: Developers
Classifier: Intended Audience :: Science/Research
Classifier: License :: OSI Approved :: MIT License
Classifier: Programming Language :: Python :: 3
Classifier: Programming Language :: Python :: 3.8
Classifier: Programming Language :: Python :: 3.9
Classifier: Programming Language :: Python :: 3.10
Classifier: Programming Language :: Python :: 3.11
Classifier: Programming Language :: Python :: 3.12
Classifier: Programming Language :: Rust
Classifier: Topic :: Scientific/Engineering :: GIS
Requires-Dist: pytest ; extra == 'dev'
Requires-Dist: maturin ; extra == 'dev'
Provides-Extra: dev
Summary: High-performance SRTM elevation data library
Keywords: srtm,elevation,gis,geography,terrain
Author-email: Pedro Sánchez Martínez <pedrosanzmtz@users.noreply.github.com>
License: MIT
Requires-Python: >=3.8
Project-URL: Homepage, https://github.com/pedrosanzmtz/htg
Project-URL: Repository, https://github.com/pedrosanzmtz/htg
Project-URL: Documentation, https://github.com/pedrosanzmtz/htg#readme
